gradio_litmodel3d/__init__.py
gradio_litmodel3d/litmodel3d.py
gradio_litmodel3d/litmodel3d.pyi
gradio_litmodel3d/templates/component/Canvas3D-Cduz95bA.js
gradio_litmodel3d/templates/component/Canvas3DGS-BNgp41cs.js
gradio_litmodel3d/templates/component/Index-DFUH5UeF.js
gradio_litmodel3d/templates/component/index.js
gradio_litmodel3d/templates/component/style.css
gradio_litmodel3d/templates/example/index.js
gradio_litmodel3d/templates/example/style.css
gradio_litmodel3d-0.0.1.dist-info/METADATA
gradio_litmodel3d-0.0.1.dist-info/WHEEL
gradio_litmodel3d-0.0.1.dist-info/RECORD
